yjt/__init__.py
yjt/db/__init__.py
yjt/db/database.py
yjt/db/sqlconstructor.py
yjt/utils/__init__.py
yjt/utils/utils_aes.py
yjt/utils/utils_captcha.py
yjt/utils/utils_dbs.py
yjt/utils/utils_md5.py
yjt/utils/utils_pil.py
yjt/utils/utils_rsa.py
yjt/utils/utils_single.py
yjt/utils/utils_string.py
yjt/utils/font/Monaco.ttf
yjt-1.1.dist-info/METADATA
yjt-1.1.dist-info/WHEEL
yjt-1.1.dist-info/entry_points.txt
yjt-1.1.dist-info/license_files/LICENSE
yjt-1.1.dist-info/RECORD
